connectionist/__about__.py
connectionist/__init__.py
connectionist/data.py
connectionist/layers.py
connectionist/losses.py
connectionist/models.py
connectionist/surgery.py
connectionist-0.2.5.dist-info/METADATA
connectionist-0.2.5.dist-info/WHEEL
connectionist-0.2.5.dist-info/licenses/LICENSE
connectionist-0.2.5.dist-info/RECORD
