Metadata-Version: 2.1
Name: connectionist
Version: 0.2.5
Summary: Tools for classical connectionist models of reading with TensorFlow
Project-URL: Homepage, https://github.com/jasonlo/connectionist
Project-URL: Documentation, https://jasonlo.github.io/connectionist/
Author-email: Jason Lo <lcmjlo@gmail.com>
License-Expression: MIT
License-File: LICENSE
Requires-Python: >=3.8
Requires-Dist: tensorflow==2.*
